browser_use_cloud_mcp/__init__.py
browser_use_cloud_mcp/cli.py
browser_use_cloud_mcp/client.py
browser_use_cloud_mcp/models.py
browser_use_cloud_mcp/server.py
browser_use_cloud_mcp-0.1.0.dist-info/LICENSE
browser_use_cloud_mcp-0.1.0.dist-info/METADATA
browser_use_cloud_mcp-0.1.0.dist-info/WHEEL
browser_use_cloud_mcp-0.1.0.dist-info/entry_points.txt
browser_use_cloud_mcp-0.1.0.dist-info/RECORD
