Metadata-Version: 2.3
Name: browser-use-cloud-mcp
Version: 0.1.0
Summary: Model Context Protocol (MCP) server for Browser Use Cloud API - automate web browsing tasks with AI
License: MIT
Keywords: mcp,browser-automation,ai,web-scraping,model-context-protocol,browser-use-cloud
Author: Pranav Prakash
Requires-Python: >=3.10,<4.0
Classifier: Development Status :: 4 - Beta
Classifier: Intended Audience :: Developers
Classifier: License :: OSI Approved :: MIT License
Classifier: Operating System :: OS Independent
Classifier: Programming Language :: Python :: 3
Classifier: Programming Language :: Python :: 3.10
Classifier: Programming Language :: Python :: 3.11
Classifier: Programming Language :: Python :: 3.12
Classifier: Programming Language :: Python :: 3.13
Classifier: Topic :: Internet :: WWW/HTTP :: Browsers
Classifier: Topic :: Scientific/Engineering :: Artificial Intelligence
Classifier: Topic :: Software Development :: Libraries :: Python Modules
Classifier: Typing :: Typed
Provides-Extra: http
Requires-Dist: fastapi (>=0.115.12,<0.116.0) ; extra == "http"
Requires-Dist: httpx (>=0.28.0,<0.29.0)
Requires-Dist: mcp[cli] (>=1.9.2,<2.0.0)
Requires-Dist: pydantic (>=2.0.0,<3.0.0)
Requires-Dist: uvicorn (>=0.34.3,<0.35.0) ; extra == "http"
Project-URL: Documentation, https://github.com/fere-ai/browser-use-cloud-mcp#readme
Project-URL: Homepage, https://github.com/fere-ai/browser-use-cloud-mcp
Project-URL: Repository, https://github.com/fere-ai/browser-use-cloud-mcp
